farcaster_cli/__init__.py
farcaster_cli/main.py
farcaster_cli-0.1.5.dist-info/WHEEL
farcaster_cli-0.1.5.dist-info/entry_points.txt
farcaster_cli-0.1.5.dist-info/METADATA
farcaster_cli-0.1.5.dist-info/RECORD
