Metadata-Version: 2.1
Name: farcaster-cli
Version: 0.1.5
Summary: Farcaster CLI Client
License: MIT
Author: Mason Hall
Author-email: masonhall@gmail.com
Requires-Python: >=3.7.2,<4.0.0
Classifier: License :: OSI Approved :: MIT License
Classifier: Programming Language :: Python :: 3
Classifier: Programming Language :: Python :: 3.8
Classifier: Programming Language :: Python :: 3.9
Classifier: Programming Language :: Python :: 3.10
Classifier: Programming Language :: Python :: 3.11
Requires-Dist: farcaster (>=0.7.4,<0.8.0)
Requires-Dist: typer[all] (>=0.7.0,<0.8.0)
